LICENSE
MANIFEST.in
README.md
setup.cfg
setup.py
src/voyandz/__init__.py
src/voyandz/cli.py
src/voyandz/config.py
src/voyandz/logging.py
src/voyandz/piping.py
src/voyandz/server.py
src/voyandz/stats.py
src/voyandz/util.py
src/voyandz/version.py
src/voyandz.egg-info/PKG-INFO
src/voyandz.egg-info/SOURCES.txt
src/voyandz.egg-info/dependency_links.txt
src/voyandz.egg-info/entry_points.txt
src/voyandz.egg-info/not-zip-safe
src/voyandz.egg-info/requires.txt
src/voyandz.egg-info/top_level.txt
src/voyandz/templates/home.html
src/voyandz/templates/stat.html