Metadata-Version: 2.1
Name: voyandz
Version: 0.3.0
Summary: an AV HTTP piping server
Home-page: https://github.com/Zalewa/voyandz
Author: Robikz
Author-email: zalewapl@gmail.com
License: MIT
Platform: UNKNOWN
